{"id":"bank_rbe-reasoning-sectional-11pysud","title":"RBE REASONING SECTIONAL","category":"RBE Sectional — Reasoning","group":"mock","source":"RBE Sectional — Reasoning","createdAt":"2026-07-13T00:00:00.000Z","questions":[{"question":"उस विकल्प आकृति का चयन कीजिए जो स्वरूप को पूरा करने के लिए दी गई आकृति में प्रश्न चिह्न (?) के स्थान पर आएगी। ![](https://appx-content-v2.classx.co.in/website/bulk_uploader_images/1738910808324_image001.png)","options":["![](https://appx-content-v2.classx.co.in/website/bulk_uploader_images/1738910808324_image002.jpeg)","![](https://appx-content-v2.classx.co.in/website/bulk_uploader_images/1738910808324_image003.jpeg)","![](https://appx-content-v2.classx.co.in/website/bulk_uploader_images/1738910808324_image004.jpeg)","![](https://appx-content-v2.classx.co.in/website/bulk_uploader_images/1738910808324_image005.jpeg)"],"answer":0,"explanation":"सही उत्तर है: a ![](https://appx-content-v2.classx.co.in/website/bulk_uploader_images/1738910808324_image002.jpeg)"},{"question":"तीन कथनों के बाद तीन निष्कर्ष I, II और III दिए गए हैं। कथनों को सत्य मानते हुए, भले ही वे आम तौर पर ज्ञात तथ्यों से भिन्न प्रतीत होते हों, तय करें कि कौन सा निष्कर्ष कथनों का तार्किक रूप से अनुसरण करता है। कथन: सभी चमगादड़ पेड़ हैं। सभी पेड़ बिल्लियाँ हैं। कुछ बिल्लियाँ हरी हैं। निष्कर्ष: I. कुछ बिल्लियाँ चमगादड़ हैं। II, सभी पेड़ हरे हैं। III. सभी हरे बिल्लियाँ हैं।","options":["केवल निष्कर्ष III अनुसरण करता है।","केवल निष्कर्ष II अनुसरण करता है।","सभी निष्कर्ष अनुसरण करते हैं।","केवल निष्कर्ष I अनुसरण करता है।"],"answer":3,"explanation":"![](https://appx-content-v2.classx.co.in/website/bulk_uploader_images/1738910808324_image006.png)"},{"question":"उस विकल्प का चयन कीजिए जो तीसरे पद से उसी प्रकार संबंधित है जिस प्रकार दूसरा पद पहले पद से संबंधित है और छठा पद पांचवें पद से संबंधित है। 59 : 3483 :: 63 : ? :: 78 : 6086","options":["3971","3969","3953","3973"],"answer":0,"explanation":"सही उत्तर है: a => 59 = ![](https://appx-content-v2.classx.co.in/website/bulk_uploader_images/1738910808324_image007.png) => 78= ![](https://appx-content-v2.classx.co.in/website/bulk_uploader_images/1738910808324_image008.png) => 63 = ![](https://appx-content-v2.classx.co.in/website/bulk_uploader_images/1738910808324_image009.png)"},{"question":"उस विकल्प का चयन कीजिए जो उन अक्षरों को दर्शाता है, जो नीचे दिए गए रिक्त स्थानों में क्रमिक रूप से बाएं से दाएं रखने पर अक्षर श्रृंखला को पूरा करेंगे। L _ _ OP _ MN _ PLM _ O _ LM _ _ P","options":["PQSTSTOQ","MNQONPNR","MNLONPNO","OPLONONO"],"answer":2,"explanation":"सही उत्तर है: c L MN OP/ L MNOP/LMNOP /LMNOP"},{"question":"उस विकल्प का चयन करें जो तीसरे शब्द से उसी तरह संबंधित है जिस तरह दूसरा शब्द पहले शब्द से संबंधित है। (शब्दों को सार्थक अंग्रेजी शब्दों के रूप में माना जाना चाहिए और शब्द में अक्षरों/व्यंजनों/स्वरों की संख्या के आधार पर एक दूसरे से संबंधित नहीं होना चाहिए) पेन : स्याही :: बल्ब : ?","options":["बिजली","स्विच","सॉकेट","प्लग"],"answer":0,"explanation":"सही उत्तर है: a • एक पेन अपना कार्य (लिखना) करने के लिए स्याही का उपयोग करता है। • एक बल्ब अपना कार्य (प्रकाश) करने के लिए बिजली का उपयोग करता है। इसलिए, \"पेन\" और \"स्याही\" के बीच का संबंध \"बल्ब\" और \"बिजली\" के बीच के संबंध जैसा ही है। इसलिए, सही विकल्प बिजली है।"},{"question":"उस विकल्प का चयन करें जिसमें दी गई आकृति अंतर्निहित है (घूर्णन की अनुमति नहीं है)। ![](https://appx-content-v2.classx.co.in/website/bulk_uploader_images/1738910808324_image010.png)","options":["![](https://appx-content-v2.classx.co.in/website/bulk_uploader_images/1738910808324_image011.jpeg)","![](https://appx-content-v2.classx.co.in/website/bulk_uploader_images/1738910808324_image012.jpeg)","![](https://appx-content-v2.classx.co.in/website/bulk_uploader_images/1738910808324_image013.jpeg)","![](https://appx-content-v2.classx.co.in/website/bulk_uploader_images/1738910808324_image014.jpeg)"],"answer":2,"explanation":"सही उत्तर है: c ![](https://appx-content-v2.classx.co.in/website/bulk_uploader_images/1738910808324_image013.jpeg)"},{"question":"छह दोस्त (A, B, C, D, E और F) एक गोलाकार मेज के चारों ओर केंद्र की ओर मुंह करके बैठे हैं। A, D के ठीक बाएं बैठा है। F, B के ठीक बाएं बैठा है। E, A का निकटतम पड़ोसी है। F, D का निकटतम पड़ोसी नहीं है। D के ठीक दाएं कौन बैठा है?","options":["A","C","E","B"],"answer":1,"explanation":"सही उत्तर है: c ![](https://appx-content-v2.classx.co.in/website/bulk_uploader_images/1738910808324_image015.png)"},{"question":"‘A + B’ का अर्थ है ‘A, B का भाई है’ ‘A – B’ का अर्थ है ‘A, B की माँ है’ ‘A × B’ का अर्थ है ‘A, B का पति है’ ‘A ÷ B’ का अर्थ है ‘A, B की बहन है’ यदि F x U - R + K + E ÷ W, तो निम्नलिखित में से कौन सा कथन सही नहीं है?","options":["E, U की बेटी है.","R, W का भाई है.","F, W के पिता का भाई है।","K, F का पुत्र है."],"answer":2,"explanation":"![](https://appx-content-v2.classx.co.in/website/bulk_uploader_images/1738910808324_image016.png)"},{"question":"एक निश्चित कोड भाषा में, ‘SELL’ को 84 और ‘MAIL’ को 53 के रूप में कोडित किया गया है। उस भाषा में ‘PROFIT’ को कैसे कोडित किया जाएगा?","options":["48","36","54","63"],"answer":0,"explanation":"सही उत्तर है: a SELL = 19+5+12+12 = 48 (sum of the place value of alphabets) Now, reverse the digits 48  84. MAIL = 13+1+9+12 = 35 Reversing the digits = 53 PROFIT = 16+18+15+6+9+20 = 84 Reversing the digit = 48(Ans.)"},{"question":"एक निश्चित कूट भाषा में, 'TRICK' को 'PXRIG' और 'MATHS' को 'HSGZN' लिखा जाता है। उस भाषा में 'DREAM' को किस प्रकार लिखा जाएगा?","options":["NZWJW","NZVIW","NZVJW","NZWIV"],"answer":1,"explanation":"सही उत्तर है: b ![](https://appx-content-v2.classx.co.in/website/bulk_uploader_images/1738910808324_image017.png)"},{"question":"विकल्पों में से उस आकृति का चयन कीजिए जो प्रश्न चिह्न (?) के स्थान पर आ सके तथा दिए गए स्वरूप को पूरा कर सके। ![](https://appx-content-v2.classx.co.in/website/bulk_uploader_images/1738910808324_image018.png)","options":["![](https://appx-content-v2.classx.co.in/website/bulk_uploader_images/1738910808324_image019.jpeg)","![](https://appx-content-v2.classx.co.in/website/bulk_uploader_images/1738910808324_image020.jpeg)","![](https://appx-content-v2.classx.co.in/website/bulk_uploader_images/1738910808324_image021.jpeg)","![](https://appx-content-v2.classx.co.in/website/bulk_uploader_images/1738910808324_image022.jpeg)"],"answer":3,"explanation":"सही उत्तर है: d ![](https://appx-content-v2.classx.co.in/website/bulk_uploader_images/1738910808324_image023.png)"},{"question":"P, Q, R, S, T, U, V और W एक वर्गाकार मेज़ के चारों ओर केंद्र की ओर मुख न करके बैठे हैं। उनमें से कुछ कोनों पर बैठे हैं जबकि कुछ भुजाओं के ठीक केंद्र पर बैठे हैं। Q, U के ठीक बाईं ओर बैठा है। U, W के ठीक बाईं ओर बैठा है। S, Q और R के बीच में बैठा है। T, P और R के बीच में बैठा है। V, P के ठीक बाईं ओर बैठा है। W, U के ठीक दाईं ओर बैठा है। T के दाईं ओर तीसरे स्थान पर कौन बैठा है?","options":["U","Q","R","S"],"answer":1,"explanation":"सही उत्तर है: b ![](https://appx-content-v2.classx.co.in/website/bulk_uploader_images/1738910808324_image024.png)"},{"question":"निम्नलिखित समीकरण को सही बनाने के लिए इसमें कौन से दो चिह्नों और दो संख्याओं को परस्पर बदलना चाहिए? 17 ÷ 2499 + 853 = 1000","options":["17 और 853, + और =","1000 और 853, + और ÷","17 और 2499, + और ÷","17 और 853, + और ÷"],"answer":3,"explanation":"सही उत्तर है: d 17 ÷ 2499 + 853 = 1000 17 और 853, + और ÷ को परस्पर बदलने पर, दिया गया समीकरण सही हो जाएगा। 853 + 2499 ![](https://appx-content-v2.classx.co.in/website/bulk_uploader_images/1738910808324_image025.png) 17 = 1000 => 853 + 147 => 1000 LHS = RHS"},{"question":"एक तस्वीर को देखकर गीता नाम की एक महिला ने कहा, \"वह मेरी बहू के पति के पिता हैं\"। गीता का तस्वीर में दिख रहे व्यक्ति से क्या संबंध है?","options":["सास","बहन","पत्नी","माँ"],"answer":2,"explanation":"सही उत्तर है: c • गीता कहती है, \"वह मेरी बहू के पति के पिता हैं।\" • गीता की बहू का पति उसका बेटा है। • गीता की बहू के पति का पिता उसका पति है। • इसलिए, गीता तस्वीर में मौजूद व्यक्ति की पत्नी है। • इसलिए, गीता तस्वीर में मौजूद व्यक्ति की पत्नी है। ![](https://appx-content-v2.classx.co.in/website/bulk_uploader_images/1738910808324_image026.png)"},{"question":"उस विकल्प का चयन कीजिए जो स्वरूप को पूरा करने के लिए दी गई आकृति में प्रश्न चिह्न (?) के स्थान पर आएगा। ![](https://appx-content-v2.classx.co.in/website/bulk_uploader_images/1738910808324_image027.png)","options":["![](https://appx-content-v2.classx.co.in/website/bulk_uploader_images/1738910808324_image028.jpeg)","![](https://appx-content-v2.classx.co.in/website/bulk_uploader_images/1738910808324_image029.jpeg)","![](https://appx-content-v2.classx.co.in/website/bulk_uploader_images/1738910808324_image030.jpeg)","![](https://appx-content-v2.classx.co.in/website/bulk_uploader_images/1738910808324_image031.jpeg)"],"answer":1,"explanation":"सही उत्तर है: b ![](https://appx-content-v2.classx.co.in/website/bulk_uploader_images/1738910808324_image029.jpeg)"},{"question":"अक्षरों के उस संयोजन का चयन कीजिए, जिसे दी गई श्रृंखला के रिक्त स्थानों में क्रमिक रूप से रखने पर श्रृंखला पूरी हो जाएगी। AAA __ BC__ DDEE __ GGG __ __ I","options":["ADFHH","BDFFH","BDFHH","BCEGH"],"answer":2,"explanation":"सही उत्तर है: c AAA/BBC/DDD/EEF/GGG/HHI"},{"question":"उस अक्षर-समूह युग्म का चयन करें जो नीचे दिए गए अक्षर-समूह युग्म में व्यक्त संबंध के समान संबंध को सर्वोत्तम रूप से दर्शाता है। QOM : YWU","options":["GEC : KMO","GFE : KLM","GEC : OMK","DFG : KMN"],"answer":2,"explanation":"सही उत्तर है: c ![](https://appx-content-v2.classx.co.in/website/bulk_uploader_images/1738910808324_image032.png)"},{"question":"निम्नलिखित में से कौन सी संख्या दी गई श्रृंखला में प्रश्न चिह्न (?) के स्थान पर आएगी? 109, 80, 57, 40, 29, ?","options":["20","26","22","24"],"answer":3,"explanation":"सही उत्तर है: d ![](https://appx-content-v2.classx.co.in/website/bulk_uploader_images/1738910808324_image033.png)"},{"question":"कौन सा विकल्प दिए गए शब्दों के सही क्रम को दर्शाता है जैसा कि वे अंग्रेजी शब्दकोश में दिखाई देंगे? 1. Tension 2. Telecom 3. Tonight 4. Touched 5. Thereby","options":["5, 2, 4, 1, 3","1, 2, 5, 3, 4","2, 5, 1, 4, 3","2, 1, 5, 3, 4"],"answer":3,"explanation":"सही उत्तर है: d (2, 1, 5, 3, 4.) सही क्रम इस प्रकार है: 2. Telecom 1. Tension 5. Thereby 3. Tonight 4. Touched"},{"question":"दिए गए कथनों और निष्कर्षों को ध्यानपूर्वक पढ़ें। यह मानते हुए कि कथनों में दी गई जानकारी सत्य है, भले ही वह सामान्यतः ज्ञात तथ्यों से भिन्न प्रतीत होती हो, तय करें कि दिए गए निष्कर्षों में से कौन सा/से निष्कर्ष कथनों का तार्किक रूप से अनुसरण करते हैं/करते हैं। कथन: 1) सभी नावें टोपियाँ हैं। 2) सभी टोपियाँ स्वेटर हैं। निष्कर्ष: I. सभी नावें स्वेटर हैं। II. सभी स्वेटर टोपियाँ हैं।","options":["केवल निष्कर्ष II अनुसरण करता है","न तो निष्कर्ष I और न ही II अनुसरण करता है","निष्कर्ष I और II दोनों अनुसरण करते हैं","केवल निष्कर्ष I अनुसरण करता है"],"answer":3,"explanation":"सही उत्तर है: d ![](https://appx-content-v2.classx.co.in/website/bulk_uploader_images/1738910808324_image034.png)"},{"question":"सात छात्र A, B, C, D, E, F और G हैं। प्रत्येक ने एक टेस्ट में अलग-अलग अंक प्राप्त किए। B ने C से अधिक अंक प्राप्त किए लेकिन F से कम अंक प्राप्त किए। D ने G से अधिक अंक प्राप्त किए, जिसने सभी में सबसे कम अंक प्राप्त किए। A ने F से अधिक लेकिन E से कम अंक प्राप्त किए। C ने D से अधिक लेकिन B से कम अंक प्राप्त किए। सभी में से दूसरे सबसे अधिक अंक किसने प्राप्त किए?","options":["F","E","B","A"],"answer":3,"explanation":"सही उत्तर है: d दिए गए प्रश्न का सही क्रम है: E>A>F>B>C>D>G इसलिए, A ने सभी में से दूसरा सबसे अधिक अंक प्राप्त किया।"},{"question":"निम्नलिखित समीकरण को सही बनाने के लिए इसमें कौन से दो चिह्नों और दो संख्याओं को परस्पर बदलना चाहिए? 456 − 121 ÷ 234 − 345 + 11 = 334","options":["345 और 121, + और ÷","234 और 121, − और ÷","456 और 121, + और −","11 और 121, + और −"],"answer":0,"explanation":"सही उत्तर है: a 456 − 121 ÷ 234 − 345 + 11 = 334 345 और 121, + और ÷ को परस्पर बदलने पर, दिया गया समीकरण सही हो जाएगा। => 456 − 345 + 234 – 121 ![](https://appx-content-v2.classx.co.in/website/bulk_uploader_images/1738910808324_image025.png) 11 = 334 LHS => 456 − 345 + 234 – 121 11 => 111 + 234 – 11 => 334 LHS = RHS"},{"question":"पाँच मित्र F, G, H, I और J एक गोलाकार मेज़ के चारों ओर केंद्र की ओर मुँह करके बैठे हैं। H, F के बाएँ तीसरे स्थान पर बैठा है। G, J के ठीक बाएँ और H के ठीक दाएँ बैठा है। I के ठीक दाएँ कौन बैठा है?","options":["J","F","G","H"],"answer":3,"explanation":"सही उत्तर है: d ![](https://appx-content-v2.classx.co.in/website/bulk_uploader_images/1738910808324_image035.png)"},{"question":"निम्नलिखित चार अक्षर-समूहों में से तीन एक निश्चित तरीके से समान हैं और एक अलग है। उस एक को चुनिए जो अलग है।","options":["EVHU","BYEX","CXFW","AZCY"],"answer":3,"explanation":"सही उत्तर है: d ![](https://appx-content-v2.classx.co.in/website/bulk_uploader_images/1738910808324_image036.png)"},{"question":"निम्नलिखित में से कौन सी संख्या दी गई श्रृंखला में प्रश्न चिह्न (?) के स्थान पर आएगी? 17, ?, 41, 58, 77, 100, 125","options":["38","26","28","32"],"answer":2,"explanation":"सही उत्तर है: c ![](https://appx-content-v2.classx.co.in/website/bulk_uploader_images/1738910808324_image037.png)"}]}