{"id":"bank_adiixabhii-blackbook-ows-1151-1200-mock-whudcd","title":"ADIIxABHII 🌺 Blackbook ows 1151-1200 Mock","category":"One Word Substitution (OWS)","group":"topic","source":"One Word Substitution (OWS)","createdAt":"2026-07-13T00:00:00.000Z","questions":[{"question":"Guide the course of a ship especially by using instruments or maps","options":["Navigate","Nectar","Negligible","Negotiator"],"answer":0},{"question":"Fluid secreted by flowers collected by bees for making honey","options":["Nectar","Neigh","Novice","Oasis"],"answer":0},{"question":"So small or unimportant as to be not worth considering","options":["Nonentity","Negligible","Null","Obscure"],"answer":1},{"question":"One who mediates in a deal or complex situation","options":["Neophyte","Nomad","Negotiator","Oculist"],"answer":2},{"question":"Sound of horses","options":["Neigh","Niche","Null","Oaf"],"answer":0},{"question":"Group of people living together in the same locality","options":["Oligarchy","Neighbourhood","Occidental","Nemesis"],"answer":1},{"question":"Deserved and unavoidable punishment for wrong doing","options":["Nihilism","Nemesis","Obituary","Nirvana"],"answer":1},{"question":"A new word coined by an author","options":["Nomenclature","Novelty","Neologism","Niche"],"answer":2},{"question":"A person who has recently started an activity","options":["Neophyte","Novice","Negotiator","Nomad"],"answer":0},{"question":"A specialist of kidney","options":["Neurologist","Nephrologist","Numerologist","Oculist"],"answer":1},{"question":"Giving undue favours to one's own kith and kin","options":["Nihilism","Nepotism","Nostalgia","Oligarchy"],"answer":1},{"question":"A doctor who studies and treats diseases of nerves","options":["Nephrologist","Neurologist","Neuroscience","Neurology"],"answer":1},{"question":"Scientific study of the nervous system and brain","options":["Neurology","Neuroscience","Niche","Null"],"answer":1},{"question":"A hollow space in a wall for a statue or ornament","options":["Niche","Oasis","Observatory","Null"],"answer":0},{"question":"Rejection of all religious and moral principles","options":["Nirvana","Nihilism","Nostalgia","Notorious"],"answer":1},{"question":"A transcendent state where there is neither suffering nor desire","options":["Nirvana","Nostalgia","Novice","Null"],"answer":0},{"question":"Occurring at night","options":["Nocturnal","Nomads","Notorious","Nursery"],"answer":0},{"question":"People of no fixed abode","options":["Nomads","Nonentity","Neophyte","Oaf"],"answer":0},{"question":"A system of naming things","options":["Numismatics","Nomenclature","Nostalgia","Novelty"],"answer":1},{"question":"An unimportant person","options":["Null","Nonentity","Negligible","Oaf"],"answer":1},{"question":"Delusion of suffering from a disease","options":["Nyctophobia","Nosomania","Oenomania","Nostalgia"],"answer":1},{"question":"Sentimental longing for a period in the past","options":["Nostalgia","Novelty","Novice","Null"],"answer":0},{"question":"Well-known for being bad // Person of evil reputation","options":["Notorious","Nomad","Niche","Obsolescent"],"answer":0},{"question":"The quality of being new and original","options":["Novelty","Neologism","Nomenclature","Niche"],"answer":0},{"question":"A person who is new to a profession without training","options":["Novice","Neophyte","Negotiator","Oaf"],"answer":0},{"question":"To reduce to nothing","options":["Null","Negligible","Nonentity","Obsolete"],"answer":0},{"question":"One who studies the occult meanings of numbers","options":["Numismatist","Numerologist","Nephrologist","Oculist"],"answer":1},{"question":"The study or collection of coins","options":["Numismatics","Nomenclature","Novice","Oasis"],"answer":0},{"question":"A person who collects coins","options":["Numismatist","Numerologist","Nomad","Oaf"],"answer":0},{"question":"A place where young plants/trees are grown for sale","options":["Oasis","Nursery","Observatory","Niche"],"answer":1},{"question":"An extreme fear of darkness","options":["Nyctophobia","Nosomania","Oenomania","Niche"],"answer":0},{"question":"A big clumsy often slow-witted person","options":["Oaf","Nomad","Nonentity","Neophyte"],"answer":0},{"question":"A fertile tract in a desert (water table surface)","options":["Oasis","Nursery","Observatory","Niche"],"answer":0},{"question":"A notice of a person's death","options":["Obituary","Oblivious","Obscure","Obsolete"],"answer":0},{"question":"Not informed about or aware of something","options":["Oblivious","Obscure","Obsolete","Obsolescent"],"answer":0},{"question":"Not clear","options":["Obscure","Obsolete","Negligible","Null"],"answer":0},{"question":"A place where astronomical observations are made","options":["Observatory","Nursery","Oasis","Niche"],"answer":0},{"question":"Passing out of use","options":["Obsolescent","Obsolete","Obscure","Oblivious"],"answer":0},{"question":"Something no longer in use","options":["Obsolete","Obsolescent","Obscure","Oblivious"],"answer":0},{"question":"Relating to the countries of the west","options":["Occidental","Oligarchy","Odyssey","Ominous"],"answer":0},{"question":"A work that would give me income","options":["Occupation","Odyssey","Oligarchy","Octagon"],"answer":0},{"question":"A geometrical figure with eight sides","options":["Octagon","Octopus","Octogenarian","Off-Centre"],"answer":0},{"question":"One who is eighty years old","options":["Octogenarian","Octagon","Octopus","Oculist"],"answer":0},{"question":"Eight armed sea creature","options":["Octopus","Octagon","Oculist","Odyssey"],"answer":0},{"question":"A person who attends to the diseases of the eye","options":["Oculist","Neurologist","Nephrologist","Numerologist"],"answer":0},{"question":"A long wandering or voyage marked by many changes","options":["Odyssey","Occupation","Occidental","Ominous"],"answer":0},{"question":"Obsession for wine","options":["Oenomania","Nosomania","Nyctophobia","Nostalgia"],"answer":0},{"question":"Not quite coinciding with a central position","options":["Off-Centre","Octagon","Ominous","Obscure"],"answer":0},{"question":"Government or rule by a small group of people","options":["Oligarchy","Nepotism","Nihilism","Occupation"],"answer":0},{"question":"Suggesting that something unpleasant is likely to happen","options":["Ominous","Obscure","Obsolete","Odyssey"],"answer":0}]}