{"id":"bank_modern-history-topic-1-advent-of-europeans-topic-2-socio-rel-zvj8nm","title":"MODERN HISTORY TOPIC 1 ADVENT OF EUROPEANS TOPIC 2 SOCIO RELIG","category":"History","group":"topic","source":"History","createdAt":"2026-07-13T00:00:00.000Z","questions":[{"question":"Who was the first Portuguese explorer to discover the sea route to India in 1498? / 1498 में भारत के लिए समुद्री मार्ग की खोज करने वाला पहला पुर्तगाली खोजकर्ता कौन था?","options":["Afonso de Albuquerque / अफोंसो डी अल्बुकर्क","Francisco de Almeida / फ्रांसिस्को डी अल्मेडा","Nuno da Cunha / नूनो दा कुन्हा","Vasco da Gama / वास्को डी गामा"],"answer":3,"explanation":"Vasco da Gama reached Calicut in 1498 during the reign of King Zamorin. / वास्को डी गामा 1498 में राजा ज़मोरिन के शासनकाल के दौरान कालीकट पहुँचा था।"},{"question":"Which Portuguese Governor introduced the \"Blue Water Policy\" (Cartaz System)? / किस पुर्तगाली गवर्नर ने \"ब्लू वाटर पॉलिसी\" (कार्टाज़ सिस्टम) की शुरुआत की थी?","options":["Nuno da Cunha / नूनो दा कुन्हा","Francisco de Almeida / फ्रांसिस्को डी अल्मेडा","Vasco da Gama / वास्को डी गामा","Afonso de Albuquerque / अफोंसो डी अल्बुकर्क"],"answer":1,"explanation":"Francisco de Almeida, the first Viceroy, introduced this policy to control trade in the Indian Ocean. / पहले वायसराय फ्रांसिस्को डी अल्मेडा ने हिंद महासागर में व्यापार को नियंत्रित करने के लिए इस नीति की शुरुआत की थी।"},{"question":"In which year did the Portuguese capture Goa from the Sultan of Bijapur? / पुर्तगालियों ने बीजापुर के सुल्तान से गोवा को किस वर्ष छीना था?","options":["1510","1498","1505","1530"],"answer":0,"explanation":"Afonso de Albuquerque captured Goa in 1510 and later abolished Sati in that region. / अफोंसो डी अल्बुकर्क ने 1510 में गोवा पर कब्जा किया और बाद में उस क्षेत्र में सती प्रथा को समाप्त कर दिया।"},{"question":"Where did the Dutch East India Company set up their first factory in 1605? / डच ईस्ट इंडिया कंपनी ने 1605 में अपनी पहली फैक्ट्री कहाँ स्थापित की थी?","options":["Pulicat / पुलिकट","Surat / सूरत","Calcutta / कलकत्ता","Masulipatnam / मसूलीपट्टनम"],"answer":3,"explanation":"The Dutch established their first factory at Masulipatnam (Andhra Pradesh) in 1605. / डचों ने 1605 में मसूलीपट्टनम (आंध्र प्रदेश) में अपनी पहली फैक्ट्री स्थापित की थी।"},{"question":"Who was the English representative who visited Jahangir's court in 1608? / 1608 में जहाँगीर के दरबार में जाने वाला अंग्रेजी प्रतिनिधि कौन था?","options":["Sir Thomas Roe / सर थॉमस रो","William Hawkins / विलियम हॉकिन्स","Hector Munro / हेक्टर मुनरो","Robert Clive / रॉबर्ट क्लाइव"],"answer":1,"explanation":"William Hawkins arrived at the Mughal court in 1608 to seek trading permissions. / विलियम हॉकिन्स 1608 में व्यापारिक अनुमति लेने के लिए मुगल दरबार में पहुँचे थे।"},{"question":"The Battle of Bedara (1759) was fought between which two powers? / बेदरा का युद्ध (1759) किन दो शक्तियों के बीच लड़ा गया था?","options":["French and Dutch / फ्रांसीसी और डच","British and French / ब्रिटिश और फ्रांसीसी","British and Portuguese / ब्रिटिश और पुर्तगाली","British and Dutch / ब्रिटिश और डच"],"answer":3,"explanation":"In the Battle of Bedara/Chinsurah, the British defeated the Dutch forces. / बेदरा/चिंसुरा के युद्ध में अंग्रेजों ने डच सेना को हराया था।"},{"question":"Which treaty ended the First Carnatic War (1744-1748)? / प्रथम कर्नाटक युद्ध (1744-1748) किस संधि के साथ समाप्त हुआ?","options":["Treaty of Pondicherry / पांडिचेरी की संधि","Treaty of Paris / पेरिस की संधि","Treaty of Aix-la-Chapelle / एक्स-ला-शापेल की संधि","Treaty of Madras / मद्रास की संधि"],"answer":2,"explanation":"The First Carnatic War ended in 1748 with the Treaty of Aix-la-Chapelle. / प्रथम कर्नाटक युद्ध 1748 में एक्स-ला-शापेल की संधि के साथ समाप्त हुआ था।"},{"question":"In which battle were the French forces led by Comte de Lally defeated by Sir Eyre Coote in 1760? / 1760 में सर आयर कूट ने किस युद्ध में काउंट डी लैली के नेतृत्व वाली फ्रांसीसी सेना को हराया था?","options":["Battle of Buxar / बक्सर का युद्ध","Battle of Ambur / अंबुर का युद्ध","Battle of Plassey / प्लासी का युद्ध","Battle of Wandiwash / वांडीवाश का युद्ध"],"answer":3,"explanation":"The Battle of Wandiwash (1760) was the decisive battle of the 3rd Carnatic War. / वांडीवाश का युद्ध (1760) तीसरे कर्नाटक युद्ध का निर्णायक युद्ध था।"},{"question":"Which Mughal Emperor issued the 'Golden Farman' to the British in 1717? / किस मुगल सम्राट ने 1717 में अंग्रेजों को 'गोल्डन फरमान' जारी किया था?","options":["Shah Alam II / शाह आलम II","Aurangzeb / औरंगजेब","Farrukhsiyar / फर्रुखसियर","Bahadur Shah I / बहादुर शाह I"],"answer":2,"explanation":"Farrukhsiyar issued the Farman allowing duty-free trade in Bengal for Rs. 3000 annually. / फर्रुखसियर ने सालाना 3000 रुपये में बंगाल में शुल्क मुक्त व्यापार की अनुमति देने वाला फरमान जारी किया था।"},{"question":"The 'Black Hole Tragedy' occurred in 1756 at which location? / 'ब्लैक होल त्रासदी' 1756 में किस स्थान पर हुई थी?","options":["Fort William / फोर्ट विलियम","Surat / सूरत","Munger / मुंगेर","Fort St. George / फोर्ट सेंट जॉर्ज"],"answer":0,"explanation":"It took place at Fort William, Calcutta, under the orders of Siraj-ud-Daulah. / यह सिराज-उद-दौला के आदेश पर फोर्ट विलियम, कलकत्ता में हुआ था।"},{"question":"Who led the British forces in the Battle of Plassey in 1757? / 1757 में प्लासी के युद्ध में ब्रिटिश सेना का नेतृत्व किसने किया था?","options":["Lord Wellesley / लॉर्ड वेलेस्ली","Robert Clive / रॉबर्ट क्लाइव","Warren Hastings / वॉरेन हेस्टिंग्स","Hector Munro / हेक्टर मुनरो"],"answer":1,"explanation":"Robert Clive defeated Nawab Siraj-ud-Daulah in the Battle of Plassey. / रॉबर्ट क्लाइव ने प्लासी के युद्ध में नवाब सिराज-उद-दौला को हराया था।"},{"question":"Which Nawab shifted his capital from Murshidabad to Munger? / किस नवाब ने अपनी राजधानी मुर्शिदाबाद से मुंगेर स्थानांतरित की थी?","options":["Siraj-ud-Daulah / सिराज-उद-दौला","Mir Qasim / मीर कासिम","Alivardi Khan / अलीवर्दी खान","Mir Jafar / मीर जाफर"],"answer":1,"explanation":"Mir Qasim shifted the capital to maintain distance from British interference. / मीर कासिम ने ब्रिटिश हस्तक्षेप से दूरी बनाए रखने के लिए राजधानी स्थानांतरित की थी।"},{"question":"In the Battle of Buxar (1764), who led the British East India Company forces? / बक्सर के युद्ध (1764) में ब्रिटिश ईस्ट इंडिया कंपनी की सेना का नेतृत्व किसने किया था?","options":["Lord Cornwallis / लॉर्ड कॉर्नवालिस","Hector Munro / हेक्टर मुनरो","Sir Eyre Coote / सर आयर कूट","Robert Clive / रॉबर्ट क्लाइव"],"answer":1,"explanation":"Hector Munro led the British to victory against the combined forces of Mir Qasim, Shuja-ud-Daula, and Shah Alam II. / हेक्टर मुनरो ने मीर कासिम, शुजा-उद-दौला और शाह आलम II की संयुक्त सेना के खिलाफ अंग्रेजों को जीत दिलाई।"},{"question":"The Treaty of Allahabad (1765) granted the 'Diwani Rights' of which regions to the British? / इलाहाबाद की संधि (1765) ने अंग्रेजों को किन क्षेत्रों के 'दीवानी अधिकार' प्रदान किए?","options":["Awadh and Punjab / अवध और पंजाब","Delhi and Agra / दिल्ली और आगरा","Bengal, Bihar, and Orissa / बंगाल, बिहार और उड़ीसा","Mysore and Maratha / मैसूर और मराठा"],"answer":2,"explanation":"Diwani rights (revenue collection) were granted by Mughal Emperor Shah Alam II. / मुगल सम्राट शाह आलम II द्वारा दीवानी अधिकार (राजस्व संग्रह) प्रदान किए गए थे।"},{"question":"Who was the British Governor who introduced the 'Dual Government' in Bengal? / बंगाल में 'द्वैध शासन' की शुरुआत करने वाला ब्रिटिश गवर्नर कौन था?","options":["Lord Dalhousie / लॉर्ड डलहौजी","Robert Clive / रॉबर्ट क्लाइव","Lord Wellesley / लॉर्ड वेलेस्ली","Warren Hastings / वॉरेन हेस्टिंग्स"],"answer":1,"explanation":"Robert Clive introduced Dual Government after the Treaty of Allahabad. / रॉबर्ट क्लाइव ने इलाहाबाद की संधि के बाद द्वैध शासन की शुरुआत की थी।"},{"question":"Which treaty ended the First Anglo-Mysore War (1767-1769)? / प्रथम आंग्ल-मैसूर युद्ध (1767-1769) किस संधि के साथ समाप्त हुआ?","options":["Treaty of Mangalore / मैंगलोर की संधि","Treaty of Seringapatnam / श्रीरंगपट्टनम की संधि","Treaty of Madras / मद्रास की संधि","Treaty of Paris / पेरिस की संधि"],"answer":2,"explanation":"The war ended with the Treaty of Madras, which was won by Hyder Ali of Mysore. / युद्ध मद्रास की संधि के साथ समाप्त हुआ, जिसे मैसूर के हैदर अली ने जीता था।"},{"question":"Hyder Ali died during which Anglo-Mysore War? / हैदर अली की मृत्यु किस आंग्ल-मैसूर युद्ध के दौरान हुई थी?","options":["2nd Anglo-Mysore War / द्वितीय आंग्ल-मैसूर युद्ध","1st Anglo-Mysore War / प्रथम आंग्ल-मैसूर युद्ध","4th Anglo-Mysore War / चतुर्थ आंग्ल-मैसूर युद्ध","3rd Anglo-Mysore War / तृतीय आंग्ल-मैसूर युद्ध"],"answer":0,"explanation":"Hyder Ali died of cancer in 1782 during the 2nd Anglo-Mysore War. / हैदर अली की मृत्यु 1782 में द्वितीय आंग्ल-मैसूर युद्ध के दौरान कैंसर से हुई थी।"},{"question":"Who was the British Governor-General who introduced the 'Subsidiary Alliance' in 1798? / 1798 में 'सहायक संधि' (Subsidiary Alliance) शुरू करने वाला ब्रिटिश गवर्नर-जनरल कौन था?","options":["Lord Cornwallis / लॉर्ड कॉर्नवालिस","Lord Hastings / लॉर्ड हेस्टिंग्स","Lord Dalhousie / लॉर्ड डलहौजी","Lord Wellesley / लॉर्ड वेलेस्ली"],"answer":3,"explanation":"Lord Wellesley used the Subsidiary Alliance to expand British influence over Indian states. / लॉर्ड वेलेस्ली ने भारतीय राज्यों पर ब्रिटिश प्रभाव बढ़ाने के लिए सहायक संधि का उपयोग किया।"},{"question":"Which state was the first to sign the 'Subsidiary Alliance' in 1798? / 1798 में 'सहायक संधि' पर हस्ताक्षर करने वाला पहला राज्य कौन सा था?","options":["Mysore / मैसूर","Hyderabad / हैदराबाद","Awadh / अवध","Tanjore / तंजौर"],"answer":1,"explanation":"The Nizam of Hyderabad was the first to accept the Subsidiary Alliance in 1798. / हैदराबाद का निजाम 1798 में सहायक संधि को स्वीकार करने वाला पहला व्यक्ति था।"},{"question":"Tipu Sultan was killed in which Anglo-Mysore War? / टीपू सुल्तान किस आंग्ल-मैसूर युद्ध में मारा गया था?","options":["3rd Anglo-Mysore War / तृतीय आंग्ल-मैसूर युद्ध","4th Anglo-Mysore War / चतुर्थ आंग्ल-मैसूर युद्ध","1st Anglo-Mysore War / प्रथम आंग्ल-मैसूर युद्ध","2nd Anglo-Mysore War / द्वितीय आंग्ल-मैसूर युद्ध"],"answer":1,"explanation":"Tipu Sultan died in 1799 while defending his capital, Seringapatnam. / टीपू सुल्तान की मृत्यु 1799 में अपनी राजधानी श्रीरंगपट्टनम की रक्षा करते हुए हुई थी।"},{"question":"The Treaty of Amritsar (1809) was signed between the British and which Sikh ruler? / अंग्रेजों और किस सिख शासक के बीच अमृतसर की संधि (1809) पर हस्ताक्षर किए गए थे?","options":["Maharaja Ranjit Singh / महाराजा रणजीत सिंह","Banda Bahadur / बंदा बहादुर","Gulab Singh / गुलाब सिंह","Maharaja Duleep Singh / महाराजा दलीप सिंह"],"answer":0,"explanation":"This treaty established the Sutlej River as the boundary between the Sikh Kingdom and the British. / इस संधि ने सतलुज नदी को सिख साम्राज्य और अंग्रेजों के बीच की सीमा के रूप में स्थापित किया।"},{"question":"Which treaty ended the First Anglo-Burma War in 1826? / 1826 में प्रथम आंग्ल-बर्मा युद्ध किस संधि के साथ समाप्त हुआ?","options":["Treaty of Gandamak / गंडमक की संधि","Treaty of Lahore / लाहौर की संधि","Treaty of Sagaing / सागाइंग की संधि","Treaty of Yandaboo / यांडाबू की संधि"],"answer":3,"explanation":"The Treaty of Yandaboo marked the end of the first conflict with Burma. / यांडाबू की संधि ने बर्मा के साथ पहले संघर्ष के अंत को चिह्नित किया।"},{"question":"During which war was the Kohinoor diamond taken by the British? / किस युद्ध के दौरान अंग्रेजों ने कोहिनूर हीरा ले लिया था?","options":["1st Anglo-Sikh War / प्रथम आंग्ल-सिख युद्ध","2nd Anglo-Sikh War / द्वितीय आंग्ल-सिख युद्ध","4th Anglo-Mysore War / चतुर्थ आंग्ल-मैसूर युद्ध","Battle of Plassey / प्लासी का युद्ध"],"answer":1,"explanation":"Following the 2nd Anglo-Sikh war (1848-49), Punjab was annexed and the diamond was surrendered. / द्वितीय आंग्ल-सिख युद्ध (1848-49) के बाद, पंजाब का विलय कर लिया गया और हीरा सौंप दिया गया।"},{"question":"Who was the Nawab of Awadh who built the 'Bara Imambara' in Lucknow? / अवध का वह नवाब कौन था जिसने लखनऊ में 'बड़ा इमामबाड़ा' बनवाया था?","options":["Saadat Khan / सआदत खान","Asaf-ud-Daula / आसफ-उद-दौला","Shuja-ud-Daula / शुजा-उद-दौला","Wajid Ali Shah / वाजिद अली शाह"],"answer":1,"explanation":"The fourth Nawab of Awadh, Asaf-ud-Daula, built the Bara Imambara. / अवध के चौथे नवाब आसफ-उद-दौला ने बड़ा इमामबाड़ा बनवाया था।"},{"question":"Which Governor-General implemented the \"Policy of Masterly Inactivity\" towards Afghanistan? / किस गवर्नर-जनरल ने अफगानिस्तान के प्रति \"कुशल अकर्मण्यता की नीति\" (Masterly Inactivity) लागू की थी?","options":["John Lawrence / जॉन लॉरेंस","Lord Auckland / लॉर्ड ऑकलैंड","Lord Mayo / लॉर्ड मेयो","Lord Lytton / लॉर्ड लिटन"],"answer":0,"explanation":"John Lawrence favored non-interference in the internal affairs of Afghanistan. / जॉन लॉरेंस ने अफगानिस्तान के आंतरिक मामलों में अहस्तक्षेप का समर्थन किया।"},{"question":"The Treaty of Gandamak (1879) was signed during which Anglo-Afghan War? / गंडमक की संधि (1879) किस आंग्ल-अफगान युद्ध के दौरान हुई थी?","options":["1st Anglo-Afghan War / प्रथम आंग्ल-अफगान युद्ध","Anglo-Sikh War / आंग्ल-सिख युद्ध","3rd Anglo-Afghan War / तृतीय आंग्ल-अफगान युद्ध","2nd Anglo-Afghan War / द्वितीय आंग्ल-अफगान युद्ध"],"answer":3,"explanation":"It was signed during the Second Anglo-Afghan War under Viceroy Lord Lytton. / यह वायसराय लॉर्ड लिटन के तहत दूसरे आंग्ल-अफगान युद्ध के दौरान हस्ताक्षरित किया गया था।"},{"question":"Where did the French establish their first factory in India in 1668? / फ्रांसीसियों ने 1668 में भारत में अपनी पहली फैक्ट्री कहाँ स्थापित की थी?","options":["Surat / सूरत","Masulipatnam / मसूलीपट्टनम","Chandernagore / चंद्रनगर","Pondicherry / पांडिचेरी"],"answer":0,"explanation":"The French established their first factory at Surat in 1668. / फ्रांसीसियों ने 1668 में सूरत में अपनी पहली फैक्ट्री स्थापित की थी।"},{"question":"Who was the first Portuguese Viceroy of India? / भारत का पहला पुर्तगाली वायसराय कौन था?","options":["Vasco da Gama / वास्को डी गामा","Afonso de Albuquerque / अफोंसो डी अल्बुकर्क","Nuno da Cunha / नूनो दा कुन्हा","Francisco de Almeida / फ्रांसिस्को डी अल्मेडा"],"answer":3,"explanation":"Francisco de Almeida was appointed as the first Viceroy in 1505. / फ्रांसिस्को डी अल्मेडा को 1505 में प्रथम वायसराय के रूप में नियुक्त किया गया था।"},{"question":"In which year was the British East India Company formed? / ब्रिटिश ईस्ट इंडिया कंपनी का गठन किस वर्ष हुआ था?","options":["1608","1600","1599","1602"],"answer":2,"explanation":"The company came into existence in 1599 and received a charter in 1600. / कंपनी 1599 में अस्तित्व में आई और 1600 में चार्टर प्राप्त किया।"},{"question":"Which river was declared as the boundary between the Sikh Kingdom and the British by the Treaty of Amritsar (1809)? / अमृतसर की संधि (1809) द्वारा किस नदी को सिख साम्राज्य और अंग्रेजों के बीच की सीमा घोषित किया गया था?","options":["Sutlej / सतलुज","Indus / सिंधु","Beas / ब्यास","Jhelum / झेलम"],"answer":0,"explanation":"The Sutlej river was fixed as the boundary to limit Maharaja Ranjit Singh's expansion. / महाराजा रणजीत सिंह के विस्तार को सीमित करने के लिए सतलुज नदी को सीमा के रूप में तय किया गया था।"},{"question":"Identify the correct chronological order of the arrival of Europeans in India: / भारत में यूरोपीय लोगों के आगमन के सही कालानुक्रमिक क्रम की पहचान करें: 1. Danes (डेन्स) 2. French (फ्रांसीसी) 3. Dutch (डच) 4. English (अंग्रेज) 5. Portuguese (पुर्तगाली) Q31. Choose the correct option / सही विकल्प चुनें","options":["5-4-3-1-2","4-5-3-1-2","5-3-1-4-2","5-3-4-1-2"],"answer":3,"explanation":"The correct order is Portuguese (1498), Dutch (1602), English (1608), Danes (1616), and French (1668). / सही क्रम पुर्तगाली (1498), डच (1602), अंग्रेज (1608), डेन्स (1616) और फ्रांसीसी (1668) है।"},{"question":"List-I (Portuguese Governor) List-II (Significant Event) I. Francisco de Almeida A. Moved capital from Cochin to Goa (1530) II. Afonso de Albuquerque B. First Portuguese Viceroy & Blue Water Policy III. Nuno da Cunha C. Captured Goa in 1510 & abolished Sati Q32. Choose the correct option / सही विकल्प चुनें","options":["I-A, II-C, III-B","I-B, II-C, III-A","I-B, II-A, III-C","I-C, II-B, III-A"],"answer":1,"explanation":"Almeida introduced Blue Water Policy; Albuquerque captured Goa; Nuno da Cunha shifted the capital to Goa. / अल्मेडा ने ब्लू वाटर पॉलिसी की शुरुआत की; अल्बुकर्क ने गोवा पर कब्जा किया; नूनो दा कुन्हा ने राजधानी को गोवा स्थानांतरित कर दिया।"},{"question":"Assertion (A): The Battle of Wandiwash (1760) ended French hopes of an empire in India. / अभिकथन (A): वांडीवाश के युद्ध (1760) ने भारत में फ्रांसीसी साम्राज्य की आशाओं को समाप्त कर दिया। Reason (R): British forces led by Sir Eyre Coote defeated the French forces led by Comte de Lally. / कारण (R): सर आयर कूट के नेतृत्व वाली ब्रिटिश सेना ने काउंट डी लैली के नेतृत्व वाली फ्रांसीसी सेना को हराया था। Q33. Choose the correct option / सही विकल्प चुनें","options":["A is true but R is false.","A is false but R is true.","Both A and R are true but R is not the correct explanation of A.","Both A and R are true and R is the correct explanation of A."],"answer":3,"explanation":"The Battle of Wandiwash was the decisive 3rd Carnatic War battle that led to British supremacy over the French. / वांडीवाश का युद्ध निर्णायक तीसरा कर्नाटक युद्ध था जिसने फ्रांसीसी पर ब्रिटिश सर्वोच्चता स्थापित की।"},{"question":"Consider the following statements regarding the Battle of Plassey (1757): / प्लासी के युद्ध (1757) के संबंध में निम्नलिखित कथनों पर विचार करें: I. It was fought between Robert Clive and Nawab Siraj-ud-Daulah. / यह रॉबर्ट क्लाइव और नवाब सिराज-उद-दौला के बीच लड़ा गया था। II. Mir Jafar, the military commander of the Nawab, supported the British. / नवाब के सैन्य कमांडर मीर जाफर ने अंग्रेजों का समर्थन किया। III. Mughal Emperor at that time was Alamgir II. / उस समय मुगल सम्राट आलमगीर द्वितीय था। Q34. Choose the correct option / सही विकल्प चुनें","options":["I, II, and III","Only II and III","Only I and III","Only I and II"],"answer":0,"explanation":"All statements are correct. Mir Jafar's betrayal led to the Nawab's defeat under Alamgir II's reign. / सभी कथन सही हैं। मीर जाफर के विश्वासघात के कारण आलमगीर द्वितीय के शासनकाल में नवाब की हार हुई।"},{"question":"Match the Treaty with the corresponding War: / संधि को संबंधित युद्ध से सुमेलित करें: I. Treaty of Aix-la-Chapelle A. 3rd Carnatic War (तृतीय कर्नाटक युद्ध) II. Treaty of Pondicherry B. 1st Carnatic War (प्रथम कर्नाटक युद्ध) III. Treaty of Paris C. 2nd Carnatic War (द्वितीय कर्नाटक युद्ध) Q35. Choose the correct option / सही विकल्प चुनें","options":["I-C, II-A, III-B","I-B, II-A, III-C","I-A, II-B, III-C","I-B, II-C, III-A"],"answer":3,"explanation":"1st War ended with Aix-la-Chapelle, 2nd with Pondicherry, and 3rd with Paris. / प्रथम युद्ध एक्स-ला-शापेल के साथ, द्वितीय पांडिचेरी के साथ और तृतीय पेरिस की संधि के साथ समाप्त हुआ।"},{"question":"Statement I: Subsidiary Alliance was introduced by Lord Wellesley in 1798. / कथन I: सहायक संधि की शुरुआत 1798 में लॉर्ड वेलेस्ली द्वारा की गई थी। Statement II: Hyderabad was the first state to sign the Subsidiary Alliance. / कथन II: हैदराबाद सहायक संधि पर हस्ताक्षर करने वाला पहला राज्य था। Q36. Choose the correct option / सही विकल्प चुनें","options":["Only Statement I is correct","Both Statement I and II are correct","Neither Statement I nor II is correct","Only Statement II is correct"],"answer":1,"explanation":"Lord Wellesley used this to bring Indian states under British protection; Hyderabad joined in 1798. / लॉर्ड वेलेस्ली ने भारतीय राज्यों को ब्रिटिश संरक्षण में लाने के लिए इसका उपयोग किया; हैदराबाद 1798 में शामिल हुआ।"},{"question":"List-I (Anglo-Mysore War) List-II (Treaty) I. 1st Anglo-Mysore War A. Treaty of Seringapatnam II. 2nd Anglo-Mysore War B. Treaty of Madras III. 3rd Anglo-Mysore War C. Treaty of Mangalore Q37. Choose the correct option / सही विकल्प चुनें","options":["I-B, II-C, III-A","I-B, II-A, III-C","I-C, II-B, III-A","I-A, II-B, III-C"],"answer":0,"explanation":"1st War: Madras; 2nd War: Mangalore; 3rd War: Seringapatnam. / प्रथम युद्ध: मद्रास; द्वितीय युद्ध: मैंगलोर; तृतीय युद्ध: श्रीरंगपट्टनम।"},{"question":"Assertion (A): The Treaty of Allahabad (1765) established Dual Government in Bengal. / अभिकथन (A): इलाहाबाद की संधि (1765) ने बंगाल में द्वैध शासन की स्थापना की। Reason (R): Revenue rights (Diwani) were held by the Company and administrative functions (Nizamat) were left with the Nawab. / कारण (R): राजस्व अधिकार (दीवानी) कंपनी के पास थे और प्रशासनिक कार्य (निजामत) नवाब के पास छोड़ दिए गए थे। Q38. Choose the correct option / सही विकल्प चुनें","options":["Both A and R are true and R is the correct explanation of A.","A is true but R is false.","Both A and R are true but R is not the correct explanation of A.","A is false but R is true."],"answer":0,"explanation":"Dual Government meant power without responsibility for the British and responsibility without power for the Nawab. / द्वैध शासन का अर्थ था अंग्रेजों के लिए बिना जिम्मेदारी के शक्ति और नवाब के लिए बिना शक्ति के जिम्मेदारी।"},{"question":"Identify the correct chronological order of the following events: / निम्नलिखित घटनाओं के सही कालानुक्रमिक क्रम की पहचान करें: 1. Battle of Buxar (बक्सर का युद्ध) 2. Battle of Plassey (प्लासी का युद्ध) 3. Black Hole Tragedy (ब्लैक होल त्रासदी) 4. Treaty of Allahabad (इलाहाबाद की संधि) Q39. Choose the correct option / सही विकल्प चुनें","options":["1-2-3-4","2-3-1-4","3-1-2-4","3-2-1-4"],"answer":3,"explanation":"Black Hole (1756) -> Plassey (1757) -> Buxar (1764) -> Allahabad (1765). / ब्लैक होल (1756) -> प्लासी (1757) -> बक्सर (1764) -> इलाहाबाद (1765)।"},{"question":"Match the following regarding British expansion: / ब्रिटिश विस्तार के संबंध में निम्नलिखित का मिलान करें: I. Treaty of Amritsar (1809) A. Maharaja Duleep Singh II. Treaty of Lahore (1846) B. Maharaja Ranjit Singh III. Treaty of Yandaboo (1826) C. First Anglo-Burma War Q40. Choose the correct option / सही विकल्प चुनें","options":["I-B, II-C, III-A","I-A, II-B, III-C","I-C, II-B, III-A","I-B, II-A, III-C"],"answer":3,"explanation":"Ranjit Singh signed Amritsar Treaty; Lahore Treaty was with Duleep Singh; Yandaboo ended the Burma war. / रणजीत सिंह ने अमृतसर संधि पर हस्ताक्षर किए; लाहौर संधि दलीप सिंह के साथ थी; यांडाबू ने बर्मा युद्ध समाप्त किया।"},{"question":"Statement I: Tipu Sultan was the ruler of Mysore who died in the 4th Anglo-Mysore War. / कथन I: टीपू सुल्तान मैसूर का शासक था जिसकी मृत्यु चौथे आंग्ल-मैसूर युद्ध में हुई थी। Statement II: He was killed in the Battle of Porto Novo. / कथन II: वह पोर्टो नोवो के युद्ध में मारा गया था। Q41. Choose the correct option / सही विकल्प चुनें","options":["Both Statement I and II are correct","Only Statement I is correct","Only Statement II is correct","Neither Statement I nor II is correct"],"answer":1,"explanation":"Tipu died in the 4th war (1799) at Seringapatnam. Hyder Ali was defeated at Porto Novo (1781). / टीपू की मृत्यु चौथे युद्ध (1799) में श्रीरंगपट्टनम में हुई थी। हैदर अली पोर्टो नोवो (1781) में हार गया था।"},{"question":"Assertion (A): The Treaty of Tordesillas (1494) was signed between Spain and Portugal. / अभिकथन (A): टोर्डेसिलस की संधि (1494) स्पेन और पुर्तगाल के बीच हस्ताक्षरित की गई थी। Reason (R): It aimed to divide the newly discovered lands outside Europe. / कारण (R): इसका उद्देश्य यूरोप के बाहर नई खोजी गई भूमि को विभाजित करना था। Q42. Choose the correct option / सही विकल्प चुनें","options":["A is true but R is false.","Both A and R are true and R is the correct explanation of A.","Both A and R are true but R is not the correct explanation of A.","A is false but R is true."],"answer":1,"explanation":"The treaty divided the world into two spheres of influence between the two maritime powers. / इस संधि ने दुनिया को दो समुद्री शक्तियों के बीच प्रभाव के दो क्षेत्रों में विभाजित कर दिया।"},{"question":"List-I (Event) List-II (British Leader) I. Battle of Buxar A. Robert Clive II. Battle of Plassey B. Sir Eyre Coote III. Battle of Wandiwash C. Hector Munro Q43. Choose the correct option / सही विकल्प चुनें","options":["I-C, II-B, III-A","I-A, II-C, III-B","I-B, II-A, III-C","I-C, II-A, III-B"],"answer":3,"explanation":"Munro led Buxar; Clive led Plassey; Coote led Wandiwash. / मुनरो ने बक्सर का; क्लाइव ने प्लासी का; कूट ने वांडीवाश का नेतृत्व किया।"},{"question":"Consider the following regarding the First Anglo-Sikh War: / प्रथम आंग्ल-सिख युद्ध के संबंध में निम्नलिखित पर विचार करें: I. Battle of Aliwal was a part of this war. / अलीवाल का युद्ध इसी युद्ध का हिस्सा था। II. It ended with the Treaty of Lahore. / यह लाहौर की संधि के साथ समाप्त हुआ। III. Lord Dalhousie was the Governor-General during this war. / इस युद्ध के दौरान लॉर्ड डलहौजी गवर्नर-जनरल थे। Q44. Choose the correct option / सही विकल्प चुनें","options":["I, II, and III","Only I and II","Only II and III","Only I and III"],"answer":1,"explanation":"Statement III is wrong because Lord Hardinge was the GG during the 1st war; Dalhousie was there during the 2nd war. / कथन III गलत है क्योंकि पहले युद्ध के दौरान लॉर्ड हार्डिंग जीजी थे; दूसरे युद्ध के दौरान डलहौजी थे।"},{"question":"Match the following regarding Afghan and Burma wars: / अफगान और बर्मा युद्धों के संबंध में निम्नलिखित का मिलान करें: I. Treaty of Yandaboo A. 2nd Anglo-Afghan War II. Treaty of Gandamak B. 1st Anglo-Burma War III. Policy of Masterly Inactivity C. John Lawrence Q45. Choose the correct option / सही विकल्प चुनें","options":["I-B, II-A, III-C","I-B, II-C, III-A","I-A, II-B, III-C","I-C, II-B, III-A"],"answer":0,"explanation":"Yandaboo (Burma), Gandamak (Afghan), Masterly Inactivity (Lawrence). / यांडाबू (बर्मा), गंडमक (अफगान), मास्टरली इनएक्टिविटी (लॉरेंस)।"},{"question":"Assertion (A): The Battle of Swally (1612) was significant for the English. / अभिकथन (A): स्वाली का युद्ध (1612) अंग्रेजों के लिए महत्वपूर्ण था। Reason (R): British forces defeated the Portuguese in this naval battle near Surat. / कारण (R): ब्रिटिश सेना ने सूरत के पास इस नौसैनिक युद्ध में पुर्तगालियों को हराया था। Q46. Choose the correct option / सही विकल्प चुनें","options":["A is false but R is true.","A is true but R is false.","Both A and R are true and R is the correct explanation of A.","Both A and R are true but R is not the correct explanation of A."],"answer":2,"explanation":"This victory helped the British gain favor in the Mughal court of Jahangir. / इस जीत ने अंग्रेजों को जहाँगीर के मुगल दरबार में कृपा प्राप्त करने में मदद की।"},{"question":"Which of the following were causes of the Battle of Buxar? / निम्नलिखित में से कौन बक्सर के युद्ध के कारण थे? 1. Mir Qasim ended Dastaks (trade permits). / मीर कासिम ने दस्तक (व्यापार परमिट) समाप्त कर दी। 2. Shift of capital from Murshidabad to Munger. / मुर्शिदाबाद से मुंगेर राजधानी का स्थानांतरण। 3. Misuse of Farman by Company officials. / कंपनी के अधिकारियों द्वारा फरमान का दुरुपयोग। Q47. Choose the correct option / सही विकल्प चुनें","options":["1, 2, and 3","1 and 2 only","1 and 3 only","2 and 3 only"],"answer":0,"explanation":"All three factors led to the conflict between Mir Qasim and the East India Company. / तीनों कारकों ने मीर कासिम और ईस्ट इंडिया कंपनी के बीच संघर्ष को जन्म दिया।"},{"question":"Statement I: Dupleix was the French Governor who originated the concept of Subsidiary Alliance. / कथन I: डुप्लेक्स वह फ्रांसीसी गवर्नर था जिसने सहायक संधि की अवधारणा को जन्म दिया था। Statement II: The 1st Carnatic War was an extension of the Austrian War of Succession. / कथन II: प्रथम कर्नाटक युद्ध ऑस्ट्रियाई उत्तराधिकार के युद्ध का विस्तार था। Q48. Choose the correct option / सही विकल्प चुनें","options":["Only Statement II is correct","Only Statement I is correct","Both Statement I and II are correct","Neither Statement I nor II is correct"],"answer":2,"explanation":"Dupleix used it first, though Wellesley formalized it. The global Anglo-French rivalry triggered the wars in India. / डुप्लेक्स ने इसका पहले इस्तेमाल किया, हालांकि वेलेस्ली ने इसे औपचारिक रूप दिया। वैश्विक आंग्ल-फ्रांसीसी प्रतिद्वंद्विता ने भारत में युद्धों को जन्म दिया।"},{"question":"List-I (State) List-II (Year of joining Subsidiary Alliance) I. Hyderabad A. 1799 II. Mysore B. 1798 III. Awadh C. 1801 Q49. Choose the correct option / सही विकल्प चुनें","options":["I-C, II-A, III-B","I-B, II-A, III-C","I-A, II-B, III-C","I-B, II-C, III-A"],"answer":1,"explanation":"Hyderabad joined in 1798, Mysore in 1799, and Awadh in 1801. / हैदराबाद 1798 में, मैसूर 1799 में और अवध 1801 में शामिल हुआ।"},{"question":"Assertion (A): Siraj-ud-Daulah was the last self-governing Nawab of Bengal. / अभिकथन (A): सिराज-उद-दौला बंगाल का अंतिम स्वशासी नवाब था। Reason (R): After his defeat at Plassey, the British appointed puppet Nawabs. / कारण (R): प्लासी में उसकी हार के बाद, अंग्रेजों ने कठपुतली नवाबों की नियुक्ति की। Q50. Choose the correct option / सही विकल्प चुनें","options":["Both A and R are true but R is not the correct explanation of A.","A is false but R is true.","A is true but R is false.","Both A and R are true and R is the correct explanation of A."],"answer":3,"explanation":"Post-Plassey, the British effectively controlled the administration through Mir Jafar and others. / प्लासी के बाद, अंग्रेजों ने मीर जाफर और अन्य के माध्यम से प्रशासन को प्रभावी ढंग से नियंत्रित किया।"},{"question":"Who introduced the \"Sunset Clause\" in the Zamindari system? / ज़मींदारी व्यवस्था में \"सूर्यास्त खंड\" (Sunset Clause) किसने पेश किया था?","options":["Lord Canning / लॉर्ड कैनिंग","Warren Hastings / वारेन हेस्टिंग्स","Lord Dalhousie / लॉर्ड डलहौजी","Lord Cornwallis / लॉर्ड कॉर्नवालिस"],"answer":3,"explanation":"Lord Cornwallis introduced the Permanent Settlement (Zamindari System) in 1793, which included the sunset clause requiring payment by a specific date. / लॉर्ड कॉर्नवालिस ने 1793 में स्थायी बंदोबस्त (ज़मींदारी व्यवस्था) की शुरुआत की थी, जिसमें एक निश्चित तिथि तक भुगतान की आवश्यकता वाला सूर्यास्त खंड शामिल था।"},{"question":"The Ryotwari System was based on which of the following economic theories? / रैयतवाड़ी प्रणाली निम्नलिखित में में से किस आर्थिक सिद्धांत पर आधारित थी?","options":["Malthusian Theory / माल्थुसियन सिद्धांत","Adam Smith’s Theory / एडम स्मिथ का सिद्धांत","Keynesian Theory / कीनेसियन सिद्धांत","Ricardian Theory of Rent / रिकार्डियन थ्योरी ऑफ रेंट"],"answer":3,"explanation":"The Ryotwari System, introduced by Munro and Reed, was based on the Ricardian Theory of Rent. / मुनरो और रीड द्वारा शुरू की गई रैयतवाड़ी प्रणाली रिकार्डियन थ्योरी ऑफ रेंट पर आधारित थी।"},{"question":"Consider the following statements regarding the Mahalwari System: / महलवाड़ी प्रणाली के संबंध में निम्नलिखित कथनों पर विचार करें: 1. It was introduced by Holt Mackenzie in Punjab and Northwestern province. / इसे पंजाब और उत्तर-पश्चिमी प्रांत में होल्ट मैकेंज़ी द्वारा पेश किया गया था। 2. The revenue was collected from the village headmen on behalf of the whole village. / पूरे गाँव की ओर से गाँव के मुखियाओं से राजस्व वसूला जाता था। Q53. Choose the correct option / सही विकल्प चुनें","options":["Only 1 / केवल 1","Neither 1 nor 2 / न तो 1 और न ही 2","Only 2 / केवल 2","Both 1 and 2"],"answer":3,"explanation":"Under the Mahalwari system, the village (Mahal) was treated as a single unit and the headman collected revenue. / महलवाड़ी व्यवस्था के तहत, गाँव (महल) को एक इकाई माना जाता था और मुखिया राजस्व वसूल करता था।"},{"question":"Which of the following novels mentions the Sanyasi Rebellion of 1763? / निम्नलिखित में से किस उपन्यास में 1763 के संन्यासी विद्रोह का उल्लेख है?","options":["Devdas / देवदास","Nil Darpan / नील दर्पण","Anand Math / आनंद मठ","Gora / गोरा"],"answer":2,"explanation":"Bankim Chandra Chatterjee's novel \"Anand Math\" provides details about the Sanyasi Rebellion. / बंकिम चंद्र चटर्जी के उपन्यास \"आनंद मठ\" में संन्यासी विद्रोह के बारे में विवरण मिलता है।"},{"question":"Who was the military commander of the Khurda kingdom who led the Paika Revolt in 1817? / खुर्दा साम्राज्य का वह सैन्य कमांडर कौन था जिसने 1817 में पाइका विद्रोह का नेतृत्व किया था?","options":["Bakshi Jagbandhu Bidyadhar","Gomdhar Konwar / गोमधर कोंवर","Sidhu Murmu / सिद्धू मुर्मू","Budho Bhagat / बुधो भगत"],"answer":0,"explanation":"Bakshi Jagbandhu was the leader of the Paika Revolt that started in Odisha. / बख्शी जगबंधु ओडिशा में शुरू हुए पाइका विद्रोह के नेता थे।"},{"question":"Match the following revolts with their primary regions: / निम्नलिखित विद्रोहों को उनके प्राथमिक क्षेत्रों के साथ सुमेलित करें: List I (Revolt) | List II (Region) 1. Ahom Revolt | A. Bengal 2. Pagal Panthis | B. Assam 3. Moplah Uprising | C. Malabar Q56. Choose the correct option / सही विकल्प चुनें","options":["1-A, 2-B, 3-C","1-C, 2-A, 3-B","1-B, 2-C, 3-A","1-B, 2-A, 3-C"],"answer":3,"explanation":"Ahom Revolt occurred in Assam, Pagal Panthis in Bengal, and Moplah in the Malabar region. / अहोम विद्रोह असम में, पागल पंथी बंगाल में और मोपला मालाबार क्षेत्र में हुआ था।"},{"question":"The Battle of Saraighat (1671) was fought between the Ahom forces and which empire? / सरायघाट की लड़ाई (1671) अहोम सेना और किस साम्राज्य के बीच लड़ी गई थी?","options":["Mughal Empire","British Empire / ब्रिटिश साम्राज्य","Sikh Empire / सिख साम्राज्य","Maratha Empire / मराठा साम्राज्य"],"answer":0,"explanation":"The Battle of Saraighat was fought between the Mughals and the Ahom Kingdom, where the Mughals were defeated. / सरायघाट की लड़ाई मुगलों और अहोम साम्राज्य के बीच लड़ी गई थी, जहाँ मुगलों की हार हुई थी।"},{"question":"Who led the Kol Mutiny of 1831? / 1831 के कोल विद्रोह का नेतृत्व किसने किया था?","options":["Lachit Borphukan / लाचित बोरफुकन","Karam Shah / करम शाह","Budho Bhagat","Birsa Munda / बिरsa मुंडा"],"answer":2,"explanation":"Budho Bhagat was the prominent leader of the Kol Mutiny in 1831. / बुधो भगत 1831 में कोल विद्रोह के प्रमुख नेता थे।"},{"question":"Regarding the Munda Uprising, consider the following assertions: / मुंडा विद्रोह के संबंध में निम्नलिखित कथनों पर विचार करें: I. It is also known as the \"Ulgulan\" Uprising. / इसे \"उलगुलान\" विद्रोह के रूप में भी जाना जाता है। II. It was fought against the \"Dikus\" (outsiders). / यह \"दिकुओं\" (बाहरी लोगों) के खिलाफ लड़ा गया था। Q59. Choose the correct option / सही विकल्प चुनें","options":["Both I and II","Neither I nor II","Only II","Only I"],"answer":0,"explanation":"Birsa Munda led the Ulgulan Uprising against the colonial land system and outsiders called Dikus. / बिरसा मुंडा ने औपनिवेशिक भूमि व्यवस्था और दिकुओं नामक बाहरी लोगों के खिलाफ उलगुलान विद्रोह का नेतृत्व किया।"},{"question":"On which date is 'Janjatiya Gaurav Diwas' celebrated in India? / भारत में 'जनजातीय गौरव दिवस' किस तिथि को मनाया जाता है?","options":["26th January / 26 जनवरी","2nd October / 2 अक्टूबर","15th August / 15 अगस्त","15th November"],"answer":3,"explanation":"15th November (Birsa Munda's birth anniversary) is celebrated as Janjatiya Gaurav Diwas. / 15 नवंबर (बिरसा मुंडा की जयंती) को जनजातीय गौरव दिवस के रूप में मनाया जाता है।"},{"question":"The Gadkari Uprising (1844) took place in which of the following regions? / गडकरी विद्रोह (1844) निम्नलिखित में से किस क्षेत्र में हुआ था?","options":["Punjab / पंजाब","Bengal / बंगाल","Odisha / ओडिशा","Kolhapur"],"answer":3,"explanation":"The Gadkari Uprising occurred in Kolhapur, Maharashtra. / गडकरी विद्रोह कोल्हापुर, महाराष्ट्र में हुआ था।"},{"question":"Assertion (A): The Santhal Rebellion (1855) occurred in the Rajmahal Hills region. / कथन (A): संथाल विद्रोह (1855) राजमहल पहाड़ियों के क्षेत्र में हुआ था। Reason (R): It was led by Sidhu and Kanhu Murmu against British exploitation. / कारण (R): इसका नेतृत्व ब्रिटिश शोषण के खिलाफ सिद्धू और कान्हू मुर्मू ने किया था। Q62. Choose the correct option / सही विकल्प चुनें","options":["A is true, R is false","Both A and R are true, but R is not the correct explanation of A","Both A and R are true, and R is the correct explanation of A","A is false, R is true"],"answer":2,"explanation":"Sidhu and Kanhu led the Santhals in the Damini-e-Koh region against colonial practices. / सिद्धू और कान्हू ने औपनिवेशिक प्रथाओं के खिलाफ दामिनी-ए-कोह क्षेत्र में संथालों का नेतृत्व किया।"},{"question":"Who wrote the famous play \"Nil Darpan\" about the Indigo Revolt? / नील विद्रोह के बारे में प्रसिद्ध नाटक \"नील दर्पण\" किसने लिखा था?","options":["Ishwar Chandra Vidyasagar / ईश्वर चंद्र विद्यासागर","Rabindranath Tagore / रवींद्रनाथ टैगोर","Bankim Chandra Chatterjee / बंकिम चंद्र चटर्जी","Dinbandhu Mitra"],"answer":3,"explanation":"Dinbandhu Mitra wrote \"Nil Darpan\" to highlight the exploitation of indigo farmers. / दीनबंधु मित्र ने नील किसानों के शोषण को उजागर करने के लिए \"नील दर्पण\" लिखा था।"},{"question":"The \"Doctrine of Lapse\" was introduced by which Governor-General? / \"व्यपगत का सिद्धांत\" (Doctrine of Lapse) किस गवर्नर-जनरल द्वारा पेश किया गया था?","options":["Lord Canning / लॉर्ड कैनिंग","Lord Dalhousie","Lord Cornwallis / लॉर्ड कॉर्नवालिस","Lord Wellesley / लॉर्ड वेलेस्ली"],"answer":1,"explanation":"Lord Dalhousie introduced the Doctrine of Lapse in 1848 to annex Indian states without male heirs. / लॉर्ड डलहौजी ने बिना पुरुष उत्तराधिकारी वाले भारतीय राज्यों को हड़पने के लिए 1848 में व्यपगत का सिद्धांत पेश किया।"},{"question":"Arrange the following states in the order they were annexed under the Doctrine of Lapse: / निम्नलिखित राज्यों को व्यपगत के सिद्धांत के तहत उनके विलय के क्रम में व्यवस्थित करें: 1. Nagpur (1854) / नागपुर 2. Satara (1848) / सतारा 3. Jhansi (1853) / झाँसी Q65. Choose the correct option / सही विकल्प चुनें","options":["2-1-3","3-2-1","1-2-3","2-3-1"],"answer":3,"explanation":"Satara was the first to be annexed in 1848, followed later by Jhansi and Nagpur. / सतारा 1848 में विलय होने वाला पहला राज्य था, उसके बाद झाँसी और नागपुर का विलय हुआ।"},{"question":"On what grounds was Awadh annexed by the British in 1856? / 1856 में अंग्रेजों ने किस आधार पर अवध का विलय किया था?","options":["War / युद्ध","Doctrine of Lapse / व्यपगत का सिद्धांत","Misgovernance / कुशासन","Subsidiary Alliance / सहायक संधि"],"answer":2,"explanation":"Dalhousie annexed Awadh in 1856 on the grounds of misgovernance. / डलहौजी ने 1856 में कुशासन के आधार पर अवध का विलय किया था।"},{"question":"Who was the last Nawab of Awadh? / अवध का अंतिम नवाब कौन था?","options":["Asaf-ud-Daula / आसफ-उद-दौला","Saadat Ali Khan / सआदत अली खान","Shuja-ud-Daula / शुजा-उद-दौला","Wajid Ali Shah"],"answer":3,"explanation":"Mirza Wajid Ali Shah was the last Nawab of Awadh before its annexation. / विलय से पहले मिर्जा वाजिद अली शाह अवध के अंतिम नवाब थे।"},{"question":"Mangal Pandey belonged to which Native Infantry at Barrackpore? / मंगल पांडे बैरकपुर की किस नेटिव इन्फैंट्री से संबंधित थे?","options":["34th NI","20th NI","19th NI","7th NI"],"answer":0,"explanation":"Mangal Pandey was a sepoy in the 34th Bengal Native Infantry. / मंगल पांडे 34वीं बंगाल नेटिव इन्फैंट्री में सिपाही थे।"},{"question":"Match the leaders of the 1857 Revolt with their centers: / 1857 के विद्रोह के नेताओं को उनके केंद्रों के साथ सुमेलित करें: Center | Leader 1. Lucknow | A. Nana Saheb 2. Kanpur | B. Begum Hazrat Mahal 3. Bihar | C. Kunwar Singh Q69. Choose the correct option / सही विकल्प चुनें","options":["1-C, 2-A, 3-B","1-B, 2-A, 3-C","1-B, 2-C, 3-A","1-A, 2-B, 3-C"],"answer":1,"explanation":"Begum Hazrat Mahal led in Lucknow, Nana Saheb in Kanpur, and Kunwar Singh in Bihar. / बेगम हजरत महल ने लखनऊ में, नाना साहेब ने कानपुर में और कुंवर सिंह ने बिहार में नेतृत्व किया।"},{"question":"Who was the British officer who suppressed the revolt in Jhansi? / झाँसी में विद्रोह को दबाने वाला ब्रिटिश अधिकारी कौन था?","options":["Henry Lawrence / हेनरी लॉरेंस","John Nicholson / जॉन निकोलसन","Colin Campbell / कॉलिन कैंपबेल","Hugh Rose"],"answer":3,"explanation":"Sir Hugh Rose led the British forces to suppress the revolt in Jhansi. / सर ह्यू रोज़ ने झाँसी में विद्रोह को दबाने के लिए ब्रिटिश सेना का नेतृत्व किया।"},{"question":"What was the original name of Rani Lakshmibai? / रानी लक्ष्मीबाई का मूल नाम क्या था?","options":["Ahilyabai / अहिल्याबाई","Manikarnika Tambe","Jijabai / जीजाबाई","Gangubai / गंगूबाई"],"answer":1,"explanation":"Her original name was Manikarnika Tambe, and she was nicknamed 'Manu'. / उनका मूल नाम मणिकर्णिका तांबे था, और उनका उपनाम 'मनु' था।"},{"question":"Who led the revolt in Faizabad and was also known as 'Danka Shah'? / फैजाबाद में विद्रोह का नेतृत्व किसने किया और उन्हें 'डंका शाह' के नाम से भी जाना जाता था?","options":["Maulvi Ahmadullah","Bakht Khan / बख्त खान","Bahadur Khan / बहादुर खान","Shah Mal / शाह मल"],"answer":0,"explanation":"Maulvi Ahmadullah of Faizabad was a prominent leader known as Danka Shah. / फैजाबाद के मौलवी अहमदउल्ला एक प्रमुख नेता थे जिन्हें डंका शाह के नाम से जाना जाता था।"},{"question":"Regarding the aftermath of the 1857 Revolt, consider these statements: / 1857 के विद्रोह के परिणामों के संबंध में, इन कथनों पर विचार करें: I. The East India Company was abolished. / ईस्ट इंडिया कंपनी को समाप्त कर दिया गया। II. The Governor-General became the Viceroy. / गवर्नर-जनरल वायसराय बन गया। Q73. Choose the correct option / सही विकल्प चुनें","options":["Only I","Neither I nor II","Both I and II","Only II"],"answer":2,"explanation":"The Government of India Act 1858 transferred power to the Crown and created the post of Viceroy. / भारत सरकार अधिनियम 1858 ने सत्ता क्राउन को हस्तांतरित कर दी और वायसराय का पद बनाया।"},{"question":"Who was the first Viceroy of India? / भारत के प्रथम वायसराय कौन थे?","options":["Lord Dalhousie / लॉर्ड डलहौजी","Lord Mayo / लॉर्ड मेयो","Lord Canning","Lord William Bentinck / लॉर्ड विलियम बेंटिक"],"answer":2,"explanation":"Lord Canning became the first Viceroy under the Act of 1858. / लॉर्ड कैनिंग 1858 के अधिनियम के तहत पहले वायसराय बने।"},{"question":"Which commission recommended restructuring the Indian Army after 1857? / 1857 के बाद किस आयोग ने भारतीय सेना के पुनर्गठन की सिफारिश की थी?","options":["Sargent Commission / सार्जेंट कमीशन","Hunter Commission / हंटर कमीशन","Peel Commission","Simon Commission / साइमन कमीशन"],"answer":2,"explanation":"The Peel Commission recommended reducing the proportion of Indian soldiers. / पील आयोग ने भारतीय सैनिकों के अनुपात को कम करने की सिफारिश की थी।"},{"question":"Who called the 1857 Revolt \"Neither First, nor National, nor a War of Independence\"? / 1857 के विद्रोह को \"न तो प्रथम, न ही राष्ट्रीय, न ही स्वतंत्रता का युद्ध\" किसने कहा था?","options":["Karl Marx / कार्ल मार्क्स","C. Majumdar","D. Savarkar / वी.डी. सावरकर","Benjamin Disraeli / बेंजामिन डिसरायली"],"answer":1,"explanation":"R.C. Majumdar famously criticized the \"First War of Independence\" label. / आर.सी. मजूमदार ने \"स्वतंत्रता के पहले युद्ध\" के लेबल की प्रसिद्ध आलोचना की थी।"},{"question":"Identify the correctly matched pairs of rebels and their titles/names: / विद्रोहियों और उनकी उपाधियों/नामों के सही सुमेलित युग्मों की पहचान करें: 1. Ishan Chandra Roy - Bidrohi Raja / ईशान चंद्र रॉय - विद्रोही राजा 2. Maulvi Ahmadullah - Danka Shah / मौलवी अहमदउल्ला - डंका शाह 3. Rani Lakshmibai - Manu / रानी लक्ष्मीबाई - मनु Q77. Choose the correct option / सही विकल्प चुनें","options":["1 and 2 only","2 and 3 only","1 and 3 only","1, 2 and 3"],"answer":3,"explanation":"All three leaders are correctly matched with their popular titles. / तीनों नेताओं को उनके लोकप्रिय शीर्षकों के साथ सही ढंग से सुमेलित किया गया है।"},{"question":"The tomb of Rani Lakshmibai is located in which city? / रानी लक्ष्मीबाई की समाधि किस शहर में स्थित है?","options":["Indore / इंदौर","Gwalior","Jhansi / झाँसी","Varanasi / वाराणसी"],"answer":1,"explanation":"Her tomb is located in Gwalior where she fought her final battle. / उनकी समाधि ग्वालियर में स्थित है जहाँ उन्होंने अपनी अंतिम लड़ाई लड़ी थी।"},{"question":"Who founded the \"Ramosi Peasant Force\" (1879) in Maharashtra? / महाराष्ट्र में \"रामोसी किसान बल\" (1879) की स्थापना किसने की?","options":["R. Ambedkar / बी.आर. अंबेडकर","Vasudev Balwant Phadke","Jyotiba Phule / ज्योतिबा फुले","Bal Gangadhar Tilak / बाल गंगाधर तिलक"],"answer":1,"explanation":"Vasudev Balwant Phadke organized the Ramosi Peasant Force against British rule. / वासुदेव बलवंत फड़के ने ब्रिटिश शासन के खिलाफ रामोसी किसान बल का गठन किया।"},{"question":"In which district did the Indigo Revolt of 1859 start? / 1859 का नील विद्रोह किस जिले में शुरू हुआ था?","options":["# 1857 REVOLT: COMPLEX MCQs #","#==============================================#","Champaran / चंपारण","Patna / पटना","Burdwan / बर्धमान","Nadia","#==============================================#"],"answer":5,"explanation":"The Indigo Revolt began in the Nadia district of Bengal. / नील विद्रोह बंगाल के नदिया जिले में शुरू हुआ था।"},{"question":"Consider the following statements regarding the Permanent Settlement (1793): / स्थायी बंदोबस्त (1793) के संबंध में निम्नलिखित कथनों पर विचार करें: 1. It was introduced by Lord Cornwallis in Bengal, Bihar, and Orissa. / इसे लॉर्ड कॉर्नवालिस द्वारा बंगाल, बिहार और उड़ीसा में पेश किया गया था। 2. The 'Sunset Clause' required zamindars to pay revenue by a specific date before sunset. / 'सूर्यास्त खंड' के तहत ज़मींदारों को सूर्यास्त से पहले एक विशिष्ट तिथि तक राजस्व का भुगतान करना आवश्यक था। Q81. Choose the correct option / सही विकल्प चुनें","options":["Only 2 / केवल 2","Both 1 and 2 / 1 और 2 दोनों","Only 1 / केवल 1","Neither 1 nor 2 / न तो 1 और न ही 2"],"answer":1,"explanation":"Lord Cornwallis introduced the Zamindari system in 1793 with a sunset clause for strict revenue collection. / लॉर्ड कॉर्नवालिस ने 1793 में राजस्व वसूली के लिए सूर्यास्त खंड के साथ ज़मींदारी प्रणाली की शुरुआत की थी।"},{"question":"Assertion (A): The Ryotwari System was based on the Ricardian Theory of Rent. / कथन (A): रैयतवाड़ी प्रणाली रिकार्डियन थ्योरी ऑफ रेंट पर आधारित थी। Reason (R): Under this system, the land revenue was paid by the farmers directly to the state. / कारण (R): इस प्रणाली के तहत, भूमि राजस्व का भुगतान किसानों द्वारा सीधे राज्य को किया जाता था। Q82. Choose the correct option / सही विकल्प चुनें","options":["Both A and R are true, but R is NOT the correct explanation of A.","A is true, but R is false.","A is false, but R is true.","Both A and R are true, and R is the correct explanation of A."],"answer":3,"explanation":"The system aimed to eliminate middle-men based on Ricardo's theory, establishing a direct link between the 'Ryot' and the State. / इस प्रणाली का उद्देश्य रिकार्डो के सिद्धांत के आधार पर बिचौलियों को खत्म करना था, जिससे 'रैयत' और राज्य के बीच सीधा संबंध स्थापित हुआ।"},{"question":"Match the following Pre-1857 Revolts with their Leaders: / 1857 से पूर्व के निम्नलिखित विद्रोहों को उनके नेताओं के साथ सुमेलित करें: List I (Revolt) | List II (Leader) 1. Santhal Rebellion | A. Gomdhar Konwar 2. Kol Mutiny | B. Sidhu and Kanhu 3. Ahom Revolt | C. Budho Bhagat Q83. Choose the correct option / सही विकल्प चुनें","options":["1-A, 2-B, 3-C","1-B, 2-C, 3-A","1-B, 2-A, 3-C","1-C, 2-B, 3-A"],"answer":1,"explanation":"Santhal Rebellion was led by Sidhu-Kanhu, Kol Mutiny by Budho Bhagat, and Ahom Revolt by Gomdhar Konwar. / संथाल विद्रोह का नेतृत्व सिद्धू-कान्हू ने, कोल विद्रोह का बुधो भगत ने और अहोम विद्रोह का गोमधर कोंवर ने किया था।"},{"question":"Regarding the Munda Uprising, consider the following assertions: / मुंडा विद्रोह के संबंध में निम्नलिखित कथनों पर विचार करें: I. It is also known as the \"Ulgulan\" Uprising. / इसे \"उलगुलान\" विद्रोह के रूप में भी जाना जाता है। II. It was a reaction against the destruction of the 'Khuntkatti System' (collective ownership). / यह 'खूंटकट्टी प्रणाली' (सामूहिक स्वामित्व) के विनाश के खिलाफ एक प्रतिक्रिया थी। III. Birsa Munda was the primary leader of this movement. / बिरसा मुंडा इस आंदोलन के प्राथमिक नेता थे। Q84. Choose the correct option / सही विकल्प चुनें","options":["Only III / केवल III","I, II and III","Only I and II / केवल I और II","Only II and III / केवल II और III"],"answer":1,"explanation":"Birsa Munda led the Ulgulan to protect the traditional Khuntkatti system against Dikus (outsiders). / बिरसा मुंडा ने दिकुओं (बाहरी लोगों) के खिलाफ पारंपरिक खूंटकट्टी प्रणाली की रक्षा के लिए उलगुलान का नेतृत्व किया।"},{"question":"Assertion (A): The Battle of Saraighat (1671) resulted in a Mughal victory over the Ahom Kingdom. / कथन (A): सरायघाट की लड़ाई (1671) में अहोम साम्राज्य पर मुगलों की जीत हुई। Reason (R): The Ahom forces were led by Lachit Borphukan. / कारण (R): अहोम सेना का नेतृत्व लाचित बोरफुकन ने किया था। Q85. Choose the correct option / सही विकल्प चुनें","options":["A is false, but R is true.","A is true, but R is false.","Both A and R are false.","Both A and R are true."],"answer":0,"explanation":"The Mughals were defeated in the Battle of Saraighat; the Ahom forces were indeed led by Lachit Borphukan. / सरायघाट की लड़ाई में मुगलों की हार हुई थी; अहोम सेना का नेतृत्व वास्तव में लाचित बोरफुकन ने किया था।"},{"question":"Arrange the following places in the correct chronological order of their annexation under the Doctrine of Lapse: / व्यपगत के सिद्धांत के तहत विलय किए गए निम्नलिखित स्थानों को सही कालानुक्रमिक क्रम में व्यवस्थित करें: 1. Satara / सतारा 2. Jhansi / झाँसी 3. Sambalpur / संबलपुर 4. Nagpur / नागपुर Q86. Choose the correct option / सही विकल्प चुनें","options":["2 - 1 - 4 - 3","4 - 3 - 2 - 1","1 - 2 - 3 - 4","1 - 3 - 2 - 4"],"answer":3,"explanation":"Order: Satara (1848), Sambalpur (1849), Jhansi (1853), Nagpur (1854). / क्रम: सतारा (1848), संबलपुर (1849), झाँसी (1853), नागपुर (1854)।"},{"question":"Consider the following regarding the Sanyasi Revolt: / संन्यासी विद्रोह के संबंध में निम्नलिखित पर विचार करें: 1. It started in the regions of Bengal and Bihar. / यह बंगाल और बिहार के क्षेत्रों में शुरू हुआ था। 2. Majnu Shah and Bhawani Pathak were prominent leaders. / मजनू शाह और भवानी पाठक प्रमुख नेता थे। 3. It is famously mentioned in Bankim Chandra Chatterjee's \"Anand Math\". / इसका प्रसिद्ध उल्लेख बंकिम चंद्र चटर्जी के \"आनंद मठ\" में है। Q87. Choose the correct option / सही विकल्प चुनें","options":["Only 1 and 3 / केवल 1 और 3","Only 2 and 3 / केवल 2 और 3","I, II and III","Only 1 and 2 / केवल 1 और 2"],"answer":2,"explanation":"All statements are correct; the revolt targeted the EIC after the famine of 1770 and pilgrim restrictions. / सभी कथन सही हैं; विद्रोह ने 1770 के अकाल और तीर्थयात्रियों पर प्रतिबंध के बाद EIC को निशाना बनाया।"},{"question":"Assertion (A): Awadh was annexed by Lord Dalhousie on the grounds of Misgovernance in 1856. / कथन (A): 1856 में लॉर्ड डलहौजी ने कुशासन के आधार पर अवध का विलय कर लिया था। Reason (R): Mirza Wajid Ali Shah was the last Nawab of Awadh. / कारण (R): मिर्जा वाजिद अली शाह अवध के अंतिम नवाब थे। Q88. Choose the correct option / सही विकल्प चुनें","options":["A is false, but R is true.","Both A and R are true, but R is NOT the correct explanation of A.","A is true, but R is false.","Both A and R are true, and R is the correct explanation of A."],"answer":1,"explanation":"Both are true facts, but the identity of the Nawab is not the \"reason\" for the annexation policy itself. / दोनों सत्य तथ्य हैं, लेकिन नवाब की पहचान स्वयं विलय नीति का \"कारण\" नहीं है।"},{"question":"Match the Centers of the 1857 Revolt with their British Suppressors: / 1857 के विद्रोह के केंद्रों को उनके ब्रिटिश दमनकारियों के साथ सुमेलित करें: List I (Center) | List II (Suppressor) 1. Delhi | A. Henry Lawrence 2. Lucknow | B. John Nicholson 3. Kanpur | C. Colin Campbell Q89. Choose the correct option / सही विकल्प चुनें","options":["1-B, 2-A, 3-C","1-B, 2-C, 3-A","1-C, 2-B, 3-A","1-A, 2-B, 3-C"],"answer":0,"explanation":"Delhi was suppressed by John Nicholson, Lucknow by Henry Lawrence/Campbell, and Kanpur by Colin Campbell. / दिल्ली का दमन जॉन निकोलसन ने, लखनऊ का हेनरी लॉरेंस/कैंपबेल ने और कानपुर का कॉलिन कैंपबेल ने किया था।"},{"question":"Regarding the Indigo Revolt (1859), consider these points: / नील विद्रोह (1859) के संबंध में इन बिंदुओं पर विचार करें: I. It started in the Nadia district of Bengal. / यह बंगाल के नदिया जिले में शुरू हुआ था। II. It was led by Digambar Biswas and Bishnucharan Biswas. / इसका नेतृत्व दिगंबर विश्वास और बिष्णुचरण विश्वास ने किया था। III. It was an unsuccessful revolt. / यह एक असफल विद्रोह था। Q90. Choose the correct option / सही विकल्प चुनें","options":["I, II and III","Only I","Only I and II","Only II and III"],"answer":2,"explanation":"The Indigo Revolt was actually a successful revolt against exploitative British planters. / नील विद्रोह वास्तव में शोषक ब्रिटिश बागान मालिकों के खिलाफ एक सफल विद्रोह था।"},{"question":"Assertion (A): The General Service Establishment Act (1856) caused deep resentment among sepoys. / कथन (A): जनरल सर्विस एस्टेब्लिशमेंट एक्ट (1856) के कारण सिपाहियों में गहरा रोष था। Reason (R): It mandated that Indian soldiers must be prepared to serve overseas, which many felt violated their religious beliefs. / कारण (R): इसमें अनिवार्य किया गया था कि भारतीय सैनिकों को समुद्र पार सेवा के लिए तैयार रहना चाहिए, जिसे कइयों ने अपने धार्मिक विश्वासों का उल्लंघन माना। Q91. Choose the correct option / सही विकल्प चुनें","options":["Both A and R are true, but R is NOT the correct explanation of A.","Both A and R are true, and R is the correct explanation of A.","A is false, but R is true.","A is true, but R is false."],"answer":1,"explanation":"Crossing the sea (Kalapani) was against the religious customs of many high-caste sepoys. / समुद्र पार करना (कालापानी) कई उच्च जाति के सिपाहियों के धार्मिक रीति-रिवाजों के खिलाफ था।"},{"question":"Which of the following statements about the 'Aftermath of 1857' are correct? / '1857 के परिणाम' के बारे में निम्नलिखित में से कौन सा कथन सही है? 1. The East India Company was abolished and Crown Rule began. / ईस्ट इंडिया कंपनी को समाप्त कर दिया गया और क्राउन शासन शुरू हुआ। 2. The Governor-General's title was changed to Viceroy. / गवर्नर-जनरल का पद बदलकर वायसराय कर दिया गया। 3. The ratio of Indian soldiers in the army was increased. / सेना में भारतीय सैनिकों का अनुपात बढ़ा दिया गया। Q92. Choose the correct option / सही विकल्प चुनें","options":["Only 2 and 3","Only 1","Only 1 and 2","1, 2 and 3"],"answer":2,"explanation":"Based on the Peel Commission, the proportion of Indian soldiers was actually reduced to prevent future revolts. / पील कमीशन के आधार पर, भविष्य के विद्रोहों को रोकने के लिए भारतीय सैनिकों का अनुपात वास्तव में कम कर दिया गया था।"},{"question":"Match the Leaders of 1857 with their specific details: / 1857 के नेताओं को उनके विशिष्ट विवरणों के साथ सुमेलित करें: Leader | Detail 1. Nana Saheb | A. Real name Manikarnika 2. Rani Lakshmibai | B. Adopted son of Baji Rao II 3. Maulvi Ahmadullah | C. Known as Danka Shah Q93. Choose the correct option / सही विकल्प चुनें","options":["1-A, 2-B, 3-C","1-B, 2-C, 3-A","1-C, 2-B, 3-A","1-B, 2-A, 3-C"],"answer":3,"explanation":"Nana Saheb was Baji Rao II's adopted son, Rani Lakshmibai was Manu, and Ahmadullah was Danka Shah. / नाना साहेब बाजीराव द्वितीय के दत्तक पुत्र थे, रानी लक्ष्मीबाई मनु थीं और अहमदउल्ला डंका शाह थे।"},{"question":"Consider the following regarding the Santhal Rebellion (1855): / संथाल विद्रोह (1855) के संबंध में निम्नलिखित पर विचार करें: I. It occurred in the region of Damini-e-Koh. / यह दामिनी-ए-कोह के क्षेत्र में हुआ था। II. Sidhu and Kanhu Murmu were the primary leaders. / सिद्धू और कान्हू मुर्मू प्राथमिक नेता थे। III. It was aimed against \"Dikus\" (outsiders) and moneylenders. / इसका उद्देश्य \"दिकुओं\" (बाहरी लोगों) और साहूकारों के खिलाफ था। Q94. Choose the correct option / सही विकल्प चुनें","options":["Only I and II","I, II and III","Only III","Only II and III"],"answer":1,"explanation":"The Santhal rebellion was a massive uprising in Jharkhand against the colonial land system and outsiders. / संथाल विद्रोह औपनिवेशिक भूमि व्यवस्था और बाहरी लोगों के खिलाफ झारखंड में एक विशाल विद्रोह था।"},{"question":"Assertion (A): The Revolt of 1857 began in Meerut on May 10, 1857. / कथन (A): 1857 का विद्रोह 10 मई, 1857 को मेरठ में शुरू हुआ था। Reason (R): Mangal Pandey was hanged on April 8, 1857, for attacking British officers in Barrackpore. / कारण (R): बैरकपुर में ब्रिटिश अधिकारियों पर हमला करने के लिए मंगल पांडे को 8 अप्रैल, 1857 को फांसी दी गई थी। Q95. Choose the correct option / सही विकल्प चुनें","options":["A is true, but R is false.","A is false, but R is true.","Both A and R are true, and R is the correct explanation of A.","Both A and R are true, but R is NOT the correct explanation of A."],"answer":3,"explanation":"Both are true events, but the execution of Mangal Pandey (Barrackpore) was a precursor, not the direct tactical reason for the Meerut outbreak. / दोनों सत्य घटनाएं हैं, लेकिन मंगल पांडे की फांसी (बैरकपुर) एक पूर्वगामी घटना थी, मेरठ विद्रोह का सीधा सामरिक कारण नहीं।"},{"question":"Identify the correct statements about the Mahalwari System: / महलवाड़ी प्रणाली के बारे में सही कथनों की पहचान करें: 1. Introduced by Holt Mackenzie. / होल्ट मैकेंज़ी द्वारा पेश किया गया। 2. Implemented in Punjab and Northwestern provinces. / पंजाब और उत्तर-पश्चिमी प्रांतों में लागू किया गया। 3. Revenue was collected from individual farmers directly. / राजस्व सीधे व्यक्तिगत किसानों से एकत्र किया गया था। Q96. Choose the correct option / सही विकल्प चुनें","options":["Only 1","Only 1 and 2","Only 2 and 3","1, 2 and 3"],"answer":1,"explanation":"In Mahalwari, revenue was collected from village headmen on behalf of the village (Mahal), not individuals. / महलवाड़ी में, राजस्व व्यक्तियों के बजाय गाँव (महाल) की ओर से गाँव के मुखियाओं से एकत्र किया जाता था।"},{"question":"Match the suppression location with the year the revolt was fully quelled: / दमन स्थान को उस वर्ष के साथ सुमेलित करें जब विद्रोह पूरी तरह से शांत हो गया था: Location | Year 1. Meerut Start | A. March 1857 2. Barrackpore Incident | B. May 1857 3. Gwalior Final Suppression | C. June 1858 Q97. Choose the correct option / सही विकल्प चुनें","options":["1-B, 2-A, 3-C","1-C, 2-B, 3-A","1-B, 2-C, 3-A","1-A, 2-B, 3-C"],"answer":0,"explanation":"The timeline follows: Barrackpore (March), Meerut (May 10), and final suppression in Gwalior (June 20, 1858). / समयरेखा इस प्रकार है: बैरकपुर (मार्च), मेरठ (10 मई), और ग्वालियर में अंतिम दमन (20 जून, 1858)।"},{"question":"Assertion (A): The Revolt of 1857 is called the \"First War of Independence\" by V.D. Savarkar. / कथन (A): वी.डी. सावरकर द्वारा 1857 के विद्रोह को \"स्वतंत्रता का पहला युद्ध\" कहा गया है। Reason (R): R.C. Majumdar agreed that it was a planned national war for independence. / कारण (R): आर.सी. मजूमदार इस बात से सहमत थे कि यह स्वतंत्रता के लिए एक नियोजित राष्ट्रीय युद्ध था। Q98. Choose the correct option / सही विकल्प चुनें","options":["A is true, but R is false.","A is false, but R is true.","Both A and R are false.","Both A and R are true."],"answer":0,"explanation":"R.C. Majumdar stated it was \"neither First, nor National, nor a War of Independence\". / आर.सी. मजूमदार ने कहा कि यह \"न तो प्रथम, न ही राष्ट्रीय, न ही स्वतंत्रता का युद्ध\" था।"},{"question":"Consider the following regarding tribal and peasant revolts: / जनजातीय और किसान विद्रोहों के संबंध में निम्नलिखित पर विचार करें: 1. Pagal Panthis (1825) - Karam Shah and Tipu Shah / पागल पंथी (1825) - करम शाह और टीपू शाह 2. Ramosi Peasant Force (1879) - Vasudev Balwant Phadke / रामोसी किसान बल (1879) - वासुदेव बलवंत फड़के 3. Pabna Revolt - Ishan Chandra Roy / पाबना विद्रोह - ईशान चंद्र रॉय Q99. Choose the correct option / सही विकल्प चुनें","options":["Only 1 and 2","Only 2 and 3","I, II and III","Only 1 and 3"],"answer":2,"explanation":"All three pairs correctly identify the movement and its primary leader. / तीनों युग्म सही ढंग से आंदोलन और उसके प्राथमिक नेता की पहचान करते हैं।"},{"question":"Identify the mismatch in the following 1857 leaders and their centers: / 1857 के निम्नलिखित नेताओं और उनके केंद्रों में गलत मिलान की पहचान करें: (a) Delhi - General Bhakt Khan (b) Bihar - Kunwar Singh (c) Bareilly - Bahadur Khan Rohilla (d) Faizabad - Shah Mal ✅ Q100. Choose the correct option / सही विकल्प चुनें","options":["(b)","(c)","(a)","(d)"],"answer":3,"explanation":"Shah Mal was a leader in Uttar Pradesh (Baraut), while Maulvi Ahmadullah was the leader in Faizabad. / शाह मल उत्तर प्रदेश (बड़ौत) में एक नेता थे, जबकि मौलवी अहमदउल्ला फैजाबाद में नेता थे।"}]}